hitmc_messages/__init__.py
hitmc_messages/dispatcher.py
hitmc_messages/message.py
hitmc_messages-0.1.0.dist-info/METADATA
hitmc_messages-0.1.0.dist-info/WHEEL
hitmc_messages-0.1.0.dist-info/top_level.txt
hitmc_messages-0.1.0.dist-info/RECORD
