Metadata-Version: 2.1
Name: hitmc-messages
Version: 0.1.0
Summary: Messages for hitmc
Home-page: https://github.com/hit-mc/hitmc-messages
Author: inclyc
Author-email: axoford@icloud.com
License: UNKNOWN
Project-URL: Bug Reports, https://github.com/hit-mc/hitmc-messages/issues
Project-URL: Source, https://github.com/hit-mc/hitmc-messages
Keywords: Chattings,PSMB,Minecraft
Platform: UNKNOWN
Classifier: Development Status :: 2 - Pre-Alpha
Classifier: Intended Audience :: Developers
Classifier: License :: OSI Approved :: Apache Software License
Classifier: Natural Language :: Chinese (Simplified)
Classifier: Natural Language :: English
Classifier: Operating System :: MacOS
Classifier: Operating System :: Microsoft :: Windows
Classifier: Operating System :: POSIX :: Linux
Classifier: Programming Language :: Python :: 3
Classifier: Programming Language :: Python :: 3.8
Classifier: Programming Language :: Python :: 3.9
Classifier: Programming Language :: Python :: 3.10
Classifier: Programming Language :: Python :: 3 :: Only
Classifier: Topic :: Utilities
Requires-Python: >=3.8, <4
